genericdiff/__init__.py
genericdiff/elemental_functions.py
genericdiff/generic_diff.py
genericdiff/vector_jacobian.py
test/__init__.py
test/test_elemental_functions.py
test/test_generic_diff.py
test/test_vector_jacobian.py
genericdiff_topcoderkitty-0.0.1.dist-info/LICENSE
genericdiff_topcoderkitty-0.0.1.dist-info/METADATA
genericdiff_topcoderkitty-0.0.1.dist-info/WHEEL
genericdiff_topcoderkitty-0.0.1.dist-info/top_level.txt
genericdiff_topcoderkitty-0.0.1.dist-info/RECORD
